geomstats/__init__.py
geomstats/_logging.py
geomstats/_mesh.py
geomstats/algebra_utils.py
geomstats/errors.py
geomstats/exceptions.py
geomstats/integrator.py
geomstats/varifold.py
geomstats/vectorization.py
geomstats/_backend/__init__.py
geomstats/_backend/_backend_config.py
geomstats/_backend/_common.py
geomstats/_backend/_dtype_utils.py
geomstats/_backend/_shared_numpy/__init__.py
geomstats/_backend/_shared_numpy/_common.py
geomstats/_backend/_shared_numpy/_dispatch.py
geomstats/_backend/_shared_numpy/linalg.py
geomstats/_backend/_shared_numpy/random.py
geomstats/_backend/autograd/__init__.py
geomstats/_backend/autograd/_common.py
geomstats/_backend/autograd/_dtype.py
geomstats/_backend/autograd/autodiff.py
geomstats/_backend/autograd/linalg.py
geomstats/_backend/autograd/random.py
geomstats/_backend/numpy/__init__.py
geomstats/_backend/numpy/_common.py
geomstats/_backend/numpy/_dtype.py
geomstats/_backend/numpy/autodiff.py
geomstats/_backend/numpy/linalg.py
geomstats/_backend/numpy/random.py
geomstats/_backend/pytorch/__init__.py
geomstats/_backend/pytorch/_common.py
geomstats/_backend/pytorch/_dtype.py
geomstats/_backend/pytorch/autodiff.py
geomstats/_backend/pytorch/linalg.py
geomstats/_backend/pytorch/random.py
geomstats/datasets/__init__.py
geomstats/datasets/_base.py
geomstats/datasets/prepare_emg_data.py
geomstats/datasets/prepare_graph_data.py
geomstats/datasets/utils.py
geomstats/datasets/data/README.md
geomstats/datasets/data/cells/cell_lines.txt
geomstats/datasets/data/cells/cells.txt
geomstats/datasets/data/cells/treatments.txt
geomstats/datasets/data/cities/README.md
geomstats/datasets/data/cities/cities.csv
geomstats/datasets/data/cities/cities.json
geomstats/datasets/data/connectomes/train_FNC.csv
geomstats/datasets/data/connectomes/train_labels.csv
geomstats/datasets/data/cube_meshes/cube_mesh_diagram.jpeg
geomstats/datasets/data/cube_meshes/faces.npy
geomstats/datasets/data/cube_meshes/vertices.npy
geomstats/datasets/data/emg/emg.csv
geomstats-2.8.0.dist-info/LICENSE.md
geomstats-2.8.0.dist-info/METADATA
geomstats-2.8.0.dist-info/WHEEL
geomstats-2.8.0.dist-info/top_level.txt
geomstats-2.8.0.dist-info/RECORD
