Metadata-Version: 2.1
Name: geomstats
Version: 2.8.0
Summary: Geometric statistics on manifolds
Author-email: Nina Miolane <nmiolane@gmail.com>
License: MIT License
Project-URL: homepage, http://github.com/geomstats/geomstats
Project-URL: documentation, https://geomstats.github.io/
Project-URL: repository, http://github.com/geomstats/geomstats
Classifier: License :: OSI Approved :: MIT License
Classifier: Development Status :: 5 - Production/Stable
Classifier: Intended Audience :: Science/Research
Classifier: Topic :: Scientific/Engineering
Classifier: Topic :: Scientific/Engineering :: Mathematics
Classifier: Topic :: Scientific/Engineering :: Artificial Intelligence
Classifier: Programming Language :: Python :: 3
Classifier: Programming Language :: Python :: 3.9
Classifier: Programming Language :: Python :: 3.10
Classifier: Programming Language :: Python :: 3.11
Classifier: Programming Language :: Python :: 3.12
Requires-Python: >=3.9
License-File: LICENSE.md
Requires-Dist: joblib>=0.17.0
Requires-Dist: matplotlib>=3.3.4
Requires-Dist: numpy>=1.18.1
Requires-Dist: pandas>=1.1.5
Requires-Dist: scikit-learn>=0.22.1
Requires-Dist: scipy>=1.9
Provides-Extra: all
Requires-Dist: geomstats[backends,dev,opt]; extra == "all"
Provides-Extra: autograd
Requires-Dist: autograd>=1.3; extra == "autograd"
Provides-Extra: backends
Requires-Dist: geomstats[autograd,pytorch]; extra == "backends"
Provides-Extra: dev
Requires-Dist: geomstats[doc,lint,test,test-scripts]; extra == "dev"
Provides-Extra: doc
Requires-Dist: jupyter; extra == "doc"
Requires-Dist: nbsphinx; extra == "doc"
Requires-Dist: nbsphinx-link; extra == "doc"
Requires-Dist: sphinx; extra == "doc"
Requires-Dist: sphinx-gallery; extra == "doc"
Requires-Dist: pydata-sphinx-theme; extra == "doc"
Provides-Extra: graph
Requires-Dist: networkx; extra == "graph"
Provides-Extra: lint
Requires-Dist: ruff; extra == "lint"
Requires-Dist: pre-commit; extra == "lint"
Provides-Extra: opt
Requires-Dist: geomstats[graph,pykeops]; extra == "opt"
Provides-Extra: pykeops
Requires-Dist: pykeops; extra == "pykeops"
Provides-Extra: pytorch
Requires-Dist: torch>=1.9.1; extra == "pytorch"
Provides-Extra: test
Requires-Dist: pytest; extra == "test"
Requires-Dist: pytest-cov; extra == "test"
Requires-Dist: coverage; extra == "test"
Requires-Dist: jupyter; extra == "test"
Requires-Dist: ipython<8.23; extra == "test"
Provides-Extra: test-scripts
Requires-Dist: scikeras; extra == "test-scripts"
Requires-Dist: tensorflow; extra == "test-scripts"
